{
	"animations": [
		{
			"offsets": [
				52,
				-102
			],
			"loop": false,
			"fps": 24,
			"anim": "singLEFT",
			"indices": [],
			"name": "Left"
		},
		{
			"offsets": [
				10,
				-106
			],
			"loop": false,
			"fps": 24,
			"anim": "singDOWN",
			"indices": [],
			"name": "Down"
		},
		{
			"offsets": [
				11,
				-43
			],
			"loop": false,
			"fps": 24,
			"anim": "singUP",
			"indices": [],
			"name": "Up"
		},
		{
			"offsets": [
				3,
				-154
			],
			"loop": false,
			"fps": 24,
			"anim": "singRIGHT",
			"indices": [],
			"name": "Right"
		},
		{
			"loop": true,
			"offsets": [
				27,
				-50
			],
			"anim": "idle",
			"fps": 24,
			"name": "Idle",
			"indices": []
		}
	],
	"vocals_file": "",
	"no_antialiasing": true,
	"image": "characters/Opeor_on_the_rocks",
	"position": [
		-130,
		-95
	],
	"healthicon": "face",
	"flip_x": false,
	"healthbar_colors": [
		0,
		0,
		0
	],
	"camera_position": [
		110,
		70
	],
	"sing_duration": 4,
	"scale": 1,
	"_editor_isPlayer": false
}